awstin/__init__.py
awstin/config.py
awstin/constants.py
awstin/environment.py
awstin/apigateway/__init__.py
awstin/apigateway/auth.py
awstin/apigateway/websocket.py
awstin/apigateway/tests/__init__.py
awstin/apigateway/tests/test_auth.py
awstin/apigateway/tests/test_websocket.py
awstin/awslambda/__init__.py
awstin/awslambda/api.py
awstin/awslambda/testing.py
awstin/awslambda/tests/__init__.py
awstin/awslambda/tests/test_awslambda.py
awstin/dynamodb/__init__.py
awstin/dynamodb/orm.py
awstin/dynamodb/table.py
awstin/dynamodb/testing.py
awstin/dynamodb/utils.py
awstin/dynamodb/tests/__init__.py
awstin/dynamodb/tests/test_dynamodb.py
awstin/dynamodb/tests/test_testing.py
awstin/dynamodb/tests/test_update_item.py
awstin/sns/__init__.py
awstin/sns/api.py
awstin/sns/testing.py
awstin/sns/tests/__init__.py
awstin/sns/tests/test_sns.py
awstin/sns/tests/test_testing.py
awstin/tests/__init__.py
awstin/tests/test_config.py
awstin/tests/test_environment.py
awstin-0.0.22.dist-info/LICENSE
awstin-0.0.22.dist-info/METADATA
awstin-0.0.22.dist-info/WHEEL
awstin-0.0.22.dist-info/top_level.txt
awstin-0.0.22.dist-info/RECORD
