Metadata-Version: 2.1
Name: awstin
Version: 0.0.22
Summary: Utilities for building and testing AWS applications in Python
Home-page: https://https://github.com/k2bd/awstin
Author: Kevin Duff
License: UNKNOWN
Platform: UNKNOWN
Classifier: Programming Language :: Python :: 3
Classifier: Operating System :: OS Independent
Classifier: Development Status :: 1 - Planning
Classifier: License :: OSI Approved :: MIT License
Classifier: Intended Audience :: Developers
Requires-Python: >=3.6
Requires-Dist: boto3
